<?xml version="1.0" encoding="UTF-8"?><record_update table="sys_db_object">
    <sys_db_object action="DELETE">
        <access>public</access>
        <actions_access>false</actions_access>
        <alter_access>false</alter_access>
        <caller_access/>
        <client_scripts_access>false</client_scripts_access>
        <configuration_access>false</configuration_access>
        <create_access>false</create_access>
        <create_access_controls>true</create_access_controls>
        <delete_access>false</delete_access>
        <extension_model/>
        <is_extendable>false</is_extendable>
        <label>Integration Source</label>
        <live_feed_enabled>false</live_feed_enabled>
        <name>sn_sap_data_int_integration_source</name>
        <number_ref/>
        <provider_class/>
        <read_access>true</read_access>
        <scriptable_table>false</scriptable_table>
        <super_class/>
        <sys_class_code/>
        <sys_class_name>sys_db_object</sys_class_name>
        <sys_class_path/>
        <sys_created_by>mayank</sys_created_by>
        <sys_created_on>2023-01-12 10:35:05</sys_created_on>
        <sys_id>277a2252879c6d50a3e3cbb4dabb35fc</sys_id>
        <sys_mod_count>0</sys_mod_count>
        <sys_name>Integration Source</sys_name>
        <sys_package display_value="Primary Data Integration with SAP" source="sn_sap_data_int">93c7f5cb875a1950fd73642d0ebb3590</sys_package>
        <sys_policy/>
        <sys_scope display_value="Primary Data Integration with SAP">93c7f5cb875a1950fd73642d0ebb3590</sys_scope>
        <sys_update_name>sys_db_object_277a2252879c6d50a3e3cbb4dabb35fc</sys_update_name>
        <sys_updated_by>mayank</sys_updated_by>
        <sys_updated_on>2023-01-12 10:35:05</sys_updated_on>
        <update_access>false</update_access>
        <user_role display_value="sn_sap_data_int.integration_source_user" name="sn_sap_data_int.integration_source_user">912e846887e69d50fd73642d0ebb3581</user_role>
        <ws_access>true</ws_access>
    </sys_db_object>
    <sys_update_version action="INSERT_OR_UPDATE">
        <action>DELETE</action>
        <application display_value="Primary Data Integration with SAP">93c7f5cb875a1950fd73642d0ebb3590</application>
        <file_path/>
        <instance_id>0b7aba5fdb8c2d104d2bac44d49619ef</instance_id>
        <instance_name>psmdev601</instance_name>
        <name>sys_db_object_277a2252879c6d50a3e3cbb4dabb35fc</name>
        <payload><![CDATA[<?xml version="1.0" encoding="UTF-8"?><record_update table="sys_db_object"><sys_db_object action="INSERT_OR_UPDATE"><access>public</access><actions_access>false</actions_access><alter_access>false</alter_access><caller_access/><client_scripts_access>false</client_scripts_access><configuration_access>false</configuration_access><create_access>false</create_access><create_access_controls>true</create_access_controls><delete_access>false</delete_access><extension_model/><is_extendable>false</is_extendable><label>Integration Source</label><live_feed_enabled>false</live_feed_enabled><name>sn_sap_data_int_integration_source</name><number_ref/><provider_class/><read_access>true</read_access><scriptable_table>false</scriptable_table><super_class/><sys_class_code/><sys_class_name>sys_db_object</sys_class_name><sys_class_path/><sys_created_by>mayank</sys_created_by><sys_created_on>2023-01-12 10:35:05</sys_created_on><sys_id>277a2252879c6d50a3e3cbb4dabb35fc</sys_id><sys_mod_count>0</sys_mod_count><sys_name>Integration Source</sys_name><sys_package display_value="Primary Data Integration with SAP" source="sn_sap_data_int">93c7f5cb875a1950fd73642d0ebb3590</sys_package><sys_policy/><sys_scope display_value="Primary Data Integration with SAP">93c7f5cb875a1950fd73642d0ebb3590</sys_scope><sys_update_name>sys_db_object_277a2252879c6d50a3e3cbb4dabb35fc</sys_update_name><sys_updated_by>mayank</sys_updated_by><sys_updated_on>2023-01-12 10:35:05</sys_updated_on><update_access>false</update_access><user_role display_value="sn_sap_data_int.integration_source_user" name="sn_sap_data_int.integration_source_user">912e846887e69d50fd73642d0ebb3581</user_role><ws_access>true</ws_access></sys_db_object></record_update>]]></payload>
        <payload_hash>882891056</payload_hash>
        <record_name>Integration Source</record_name>
        <reverted_from/>
        <source>1f02639a8754a51063060e94dabb3545</source>
        <source_table>sys_update_set</source_table>
        <state>previous</state>
        <sys_created_by>Mayank</sys_created_by>
        <sys_created_on>2023-01-12 14:35:35</sys_created_on>
        <sys_id>e322e39a8754a51063060e94dabb354a</sys_id>
        <sys_mod_count>0</sys_mod_count>
        <sys_recorded_at>185a6685e0b0000001</sys_recorded_at>
        <sys_updated_by>Mayank</sys_updated_by>
        <sys_updated_on>2023-01-12 14:35:35</sys_updated_on>
        <type>Table</type>
        <update_guid>643b6e523e9c6d5027d5bf5e77047d96</update_guid>
        <update_guid_history>643b6e523e9c6d5027d5bf5e77047d96:882891056</update_guid_history>
    </sys_update_version>
    <sys_metadata_delete action="INSERT_OR_UPDATE">
        <sys_audit_delete/>
        <sys_class_name>sys_metadata_delete</sys_class_name>
        <sys_created_by>Mayank</sys_created_by>
        <sys_created_on>2023-02-28 07:48:45</sys_created_on>
        <sys_db_object display_value="" name="sys_db_object">sys_db_object</sys_db_object>
        <sys_id>849cb6c0609941f18b4146c0a64516c1</sys_id>
        <sys_metadata>277a2252879c6d50a3e3cbb4dabb35fc</sys_metadata>
        <sys_mod_count>0</sys_mod_count>
        <sys_name>Integration Source</sys_name>
        <sys_package display_value="Primary Data Integration with SAP" source="sn_sap_data_int">93c7f5cb875a1950fd73642d0ebb3590</sys_package>
        <sys_parent/>
        <sys_policy/>
        <sys_scope display_value="Primary Data Integration with SAP">93c7f5cb875a1950fd73642d0ebb3590</sys_scope>
        <sys_scope_delete display_value="">3b1319908ebb4a548e7d16c1ed008664</sys_scope_delete>
        <sys_update_name>sys_db_object_277a2252879c6d50a3e3cbb4dabb35fc</sys_update_name>
        <sys_update_version display_value="sys_db_object_277a2252879c6d50a3e3cbb4dabb35fc">e322e39a8754a51063060e94dabb354a</sys_update_version>
        <sys_updated_by>Mayank</sys_updated_by>
        <sys_updated_on>2023-02-28 07:48:45</sys_updated_on>
    </sys_metadata_delete>
</record_update>
